pisoworks/__main__.py
pisoworks/about_dialog.py
pisoworks/about_dialog.ui
pisoworks/action_manager.py
pisoworks/assets/__init__.py
pisoworks/assets/app_icon.ico
pisoworks/assets/app_icon.xcf
pisoworks/assets/dark_palette.json
pisoworks/assets/icon_piezosystem.png
pisoworks/assets/images/app_icon.svg
pisoworks/assets/images/app_icon_brand.svg
pisoworks/assets/images/cl_toggle01.svg
pisoworks/assets/images/cl_toggle02.svg
pisoworks/assets/images/cl_toggle_switch.svg
pisoworks/assets/images/modsrc_toggle01.svg
pisoworks/assets/images/modsrc_toggle02.svg
pisoworks/assets/images/modsrc_toggle03.svg
pisoworks/assets/images/modsrc_toggle04.svg
pisoworks/assets/images/modsrc_toggle2_01.svg
pisoworks/assets/images/modsrc_toggle2_02.svg
pisoworks/assets/images/modsrc_toggle2_03.svg
pisoworks/assets/images/modsrc_toggle2_04.svg
pisoworks/assets/images/modsrc_toggle_switch.svg
pisoworks/assets/images/modsrc_toggle_switch2.svg
pisoworks/assets/images/nv200_controller_structure.svg
pisoworks/assets/images/nv200_controller_structure@2x.png
pisoworks/assets/images/nv200_controller_structure_dark@2x.png
pisoworks/assets/images/piezosystem_logo@2x.png
pisoworks/assets/images/piezosystem_logo_white@2x.png
pisoworks/assets/stylesheets/ads/close-button-black.svg
pisoworks/assets/stylesheets/ads/close-button-disabled.svg
pisoworks/assets/stylesheets/ads/close-button-white.svg
pisoworks/assets/stylesheets/ads/detach-button-black.svg
pisoworks/assets/stylesheets/ads/detach-button-disabled.svg
pisoworks/assets/stylesheets/ads/detach-button-white.svg
pisoworks/assets/stylesheets/ads/maximize-button-black.svg
pisoworks/assets/stylesheets/ads/maximize-button-white.svg
pisoworks/assets/stylesheets/ads/minimize-button-black.svg
pisoworks/assets/stylesheets/ads/minimize-button-focused.svg
pisoworks/assets/stylesheets/ads/minimize-button-white.svg
pisoworks/assets/stylesheets/ads/pin-button-horizontal-black.svg
pisoworks/assets/stylesheets/ads/pin-button-horizontal-white.svg
pisoworks-2.0.1.dist-info/METADATA
pisoworks-2.0.1.dist-info/WHEEL
pisoworks-2.0.1.dist-info/entry_points.txt
pisoworks-2.0.1.dist-info/RECORD
