Metadata-Version: 2.4
Name: pisoworks
Version: 2.0.1
Summary: PySide6-based application for controlling NV200 devices.
Author: piezosystem jena GmbH
Requires-Python: >=3.12,<3.14
Classifier: Development Status :: 5 - Production/Stable
Classifier: Intended Audience :: Developers
Classifier: Intended Audience :: End Users/Desktop
Classifier: Intended Audience :: Science/Research
Classifier: Operating System :: OS Independent
Classifier: Programming Language :: Python :: 3
Classifier: Programming Language :: Python :: 3.12
Classifier: Programming Language :: Python :: 3.13
Requires-Dist: matplotlib (>=3.10.1,<4.0.0)
Requires-Dist: numpy (>=2.3.1,<3.0.0)
Requires-Dist: nv200
Requires-Dist: openpyxl (>=3.1.5,<4.0.0)
Requires-Dist: pandas (>=2.3.1,<3.0.0)
Requires-Dist: pyside6 (>=6.9.0,<7.0.0)
Requires-Dist: pyside6-qtads (>=4.4.0,<5.0.0)
Requires-Dist: qt-material-icons (>=0.2.0,<0.3.0)
Requires-Dist: qtass-pyside6 (>=0.9.2,<0.10.0)
Requires-Dist: qtawesome (>=1.4.0,<2.0.0)
Requires-Dist: qtinter (>=0.11.0,<0.12.0)
Requires-Dist: rich (>=14.0.0,<15.0.0)
Requires-Dist: scipy (>=1.16.0,<2.0.0)
Requires-Dist: tomlkit (>=0.13.2,<0.14.0)
Project-URL: Bug Tracker, https://github.com/piezosystemjena/PiSoWorks/issues
Project-URL: Documentation, https://piezosystemjena.github.io/PiSoWorks
Project-URL: Homepage, https://github.com/piezosystemjena/PiSoWorks
Project-URL: Source, https://github.com/piezosystemjena/PiSoWorks
